BurpSuiteShizhanZhinan/README.md
BurpSuiteShizhanZhinan/__init__.py
BurpSuiteShizhanZhinan/__main__.py
BurpSuiteShizhanZhinan/file.epub
BurpSuiteShizhanZhinan/index.html
BurpSuiteShizhanZhinan/css/__init__.py
BurpSuiteShizhanZhinan/css/annotations.css
BurpSuiteShizhanZhinan/css/main.css
BurpSuiteShizhanZhinan/css/normalize.css
BurpSuiteShizhanZhinan/css/popup.css
BurpSuiteShizhanZhinan/font/__init__.py
BurpSuiteShizhanZhinan/font/fontello.eot
BurpSuiteShizhanZhinan/font/fontello.svg
BurpSuiteShizhanZhinan/font/fontello.ttf
BurpSuiteShizhanZhinan/font/fontello.woff
BurpSuiteShizhanZhinan/img/__init__.py
BurpSuiteShizhanZhinan/img/annotator-glyph-sprite.png
BurpSuiteShizhanZhinan/img/annotator-icon-sprite.png
BurpSuiteShizhanZhinan/img/apple-touch-icon.png
BurpSuiteShizhanZhinan/img/cancelfullscreen.png
BurpSuiteShizhanZhinan/img/close.png
BurpSuiteShizhanZhinan/img/fullscreen.png
BurpSuiteShizhanZhinan/img/loader.gif
BurpSuiteShizhanZhinan/img/menu-icon.png
BurpSuiteShizhanZhinan/img/save.png
BurpSuiteShizhanZhinan/img/saved.png
BurpSuiteShizhanZhinan/img/settings-s.png
BurpSuiteShizhanZhinan/img/settings.png
BurpSuiteShizhanZhinan/img/star.png
BurpSuiteShizhanZhinan/js/__init__.py
BurpSuiteShizhanZhinan/js/epub.js
BurpSuiteShizhanZhinan/js/epub.min.js
BurpSuiteShizhanZhinan/js/epub.min.map
BurpSuiteShizhanZhinan/js/hooks.min.js
BurpSuiteShizhanZhinan/js/hooks.min.map
BurpSuiteShizhanZhinan/js/reader.js
BurpSuiteShizhanZhinan/js/reader.js.map
BurpSuiteShizhanZhinan/js/reader.min.js
BurpSuiteShizhanZhinan/js/reader.min.map
BurpSuiteShizhanZhinan/js/hooks/__init__.py
BurpSuiteShizhanZhinan/js/hooks/extensions/__init__.py
BurpSuiteShizhanZhinan/js/hooks/extensions/highlight.js
BurpSuiteShizhanZhinan/js/libs/__init__.py
BurpSuiteShizhanZhinan/js/libs/jquery.min.js
BurpSuiteShizhanZhinan/js/libs/localforage.min.js
BurpSuiteShizhanZhinan/js/libs/screenfull.js
BurpSuiteShizhanZhinan/js/libs/screenfull.min.js
BurpSuiteShizhanZhinan/js/libs/zip.min.js
burp_suite_shizhan_zhinan-2024.3.1.0.dist-info/METADATA
burp_suite_shizhan_zhinan-2024.3.1.0.dist-info/WHEEL
burp_suite_shizhan_zhinan-2024.3.1.0.dist-info/entry_points.txt
burp_suite_shizhan_zhinan-2024.3.1.0.dist-info/top_level.txt
burp_suite_shizhan_zhinan-2024.3.1.0.dist-info/RECORD
